setup.py
sqlbean/__init__.py
sqlbean/mc_total.py
sqlbean/mcmodel.py
sqlbean/metamodel.py
sqlbean/model.py
sqlbean/shortcut.py
sqlbean/util.py
sqlbean.egg-info/PKG-INFO
sqlbean.egg-info/SOURCES.txt
sqlbean.egg-info/dependency_links.txt
sqlbean.egg-info/not-zip-safe
sqlbean.egg-info/requires.txt
sqlbean.egg-info/top_level.txt
sqlbean/db/__init__.py
sqlbean/db/connection.py
sqlbean/db/lrucache.py
sqlbean/db/mc.py
sqlbean/db/mc_connection.py
sqlbean/db/query.py
sqlbean/db/relations.py
sqlbean/db/sqlstore.py
sqlbean/db/use_sqlite.py
sqlbean/example/__init__.py
sqlbean/example/dbutil_example.py
sqlbean/example/mysqldb_example.py
sqlbean/example/sqlfarm_example.py
sqlbean/example/sqlite_example.py