Metadata-Version: 1.0
Name: sqlbean
Version: 0.602
Summary: A auto maping ORM for MYSQL and can bind with memcached
Home-page: UNKNOWN
Author: zsp
Author-email: zsp007@gmail.com
License: UNKNOWN
Platform: UNKNOWN
